MANIFEST.in
requirements.txt
setup.py
jstestnetlib/__init__.py
jstestnetlib/control.py
jstestnetlib/noseplugins.py
jstestnetlib/webapp.py
jstestnetlib.egg-info/PKG-INFO
jstestnetlib.egg-info/SOURCES.txt
jstestnetlib.egg-info/dependency_links.txt
jstestnetlib.egg-info/entry_points.txt
jstestnetlib.egg-info/requires.txt
jstestnetlib.egg-info/top_level.txt
jstestnetlib/tests/__init__.py
jstestnetlib/tests/test_webapp.py