Metadata-Version: 1.0
Name: jstestnetlib
Version: 0.3
Summary: Client library to execute JavaScript tests against a JS TestNet
Home-page: https://github.com/kumar303/jstestnetlib
Author: Kumar McMillan
Author-email: kumar.mcmillan@gmail.com
License: Apache License
Platform: UNKNOWN
Classifier: Intended Audience :: Developers
Classifier: Natural Language :: English
Classifier: Operating System :: OS Independent
Classifier: Topic :: Software Development :: Testing
